_rust_native/__init__.py
_rust_native/__init__.pyi
_rust_native/_rust_native.cpython-311-x86_64-linux-gnu.so
_rust_native/py.typed
mandelbrot_implementation_rust_native-0.1.0.dist-info/METADATA
mandelbrot_implementation_rust_native-0.1.0.dist-info/WHEEL
mandelbrot_implementation_rust_native-0.1.0.dist-info/RECORD
